cubicweb_treeview/__init__.py
cubicweb_treeview/__pkginfo__.py
cubicweb_treeview/adapters.py
cubicweb_treeview/data/cubes.treeview.css
cubicweb_treeview/data/cubes.treeview.js
cubicweb_treeview/i18n/en.po
cubicweb_treeview/i18n/es.po
cubicweb_treeview/i18n/fr.po
cubicweb_treeview/migration/postcreate.py
cubicweb_treeview/views/__init__.py
cubicweb_treeview/views/formwidgets.py
cubicweb_treeview/views/treeview.py
cubicweb_treeview-1.0.0.dist-info/METADATA
cubicweb_treeview-1.0.0.dist-info/WHEEL
cubicweb_treeview-1.0.0.dist-info/entry_points.txt
cubicweb_treeview-1.0.0.dist-info/top_level.txt
cubicweb_treeview-1.0.0.dist-info/RECORD
